CRRM/CRRM_core_07.py
CRRM/CRRM_core_08.py
CRRM/CRRM_data_02.py
CRRM/CRRM_layout_plot_03.py
CRRM/InH_pathloss_model_01.py
CRRM/MCS_lookup_tables.py
CRRM/MIMO_channel_splines.py
CRRM/RMa_pathloss_model_08.py
CRRM/UMa_pathloss_model_06.py
CRRM/UMi_pathloss_model_00.py
CRRM/__init__.py
CRRM/geometry_3d.py
CRRM/hexagon_lattice_generator_02.py
CRRM/poisson_point_process_generator.py
CRRM/power_law_pathloss_model_02.py
CRRM/utilities.py
crrm-2.0.2.dist-info/METADATA
crrm-2.0.2.dist-info/WHEEL
crrm-2.0.2.dist-info/licenses/LICENSE
crrm-2.0.2.dist-info/RECORD
