Metadata-Version: 2.4
Name: CRRM
Version: 2.0.2
Summary: CRRM 5G system-level simulator
Project-URL: homepage, https://github.com/keithbriggs/CRRM-2.0
Project-URL: documentation, https://crrm-20.readthedocs.io/
Author-email: Keith Briggs <k.briggs73@btinternet.com>
License-File: LICENSE
Keywords: 5G,cellular radio,simulation
Classifier: License :: OSI Approved :: MIT License
Classifier: Operating System :: OS Independent
Classifier: Programming Language :: Python :: 3
Requires-Python: >=3.10
Requires-Dist: matplotlib>=3.6
Requires-Dist: numpy>=1.23
